steghub/__init__.py
steghub/cli.py
steghub-1.0.0.dist-info/licenses/LICENSE
steghub-1.0.0.dist-info/METADATA
steghub-1.0.0.dist-info/WHEEL
steghub-1.0.0.dist-info/entry_points.txt
steghub-1.0.0.dist-info/top_level.txt
steghub-1.0.0.dist-info/RECORD
