Metadata-Version: 2.4
Name: steghub
Version: 1.0.0
Summary: Advanced steganography toolkit - installs all StegHub tools
Author-email: kaizoku73 <ultimate0134@gmail.com>
License: MIT
Project-URL: Homepage, https://github.com/kaizoku73/StegHub
Project-URL: Repository, https://github.com/kaizoku73/StegHub
Project-URL: Bug Reports, https://github.com/kaizoku73/StegHub/issues
Project-URL: Documentation, https://kaizoku.gitbook.io/steganography/
Keywords: steganography,toolkit,meta-package,gradus,resono,shadowbits
Classifier: Development Status :: 5 - Production/Stable
Classifier: Intended Audience :: Developers
Classifier: Intended Audience :: End Users/Desktop
Classifier: Topic :: Security :: Cryptography
Classifier: License :: OSI Approved :: MIT License
Classifier: Programming Language :: Python :: 3
Classifier: Programming Language :: Python :: 3.7
Classifier: Programming Language :: Python :: 3.8
Classifier: Programming Language :: Python :: 3.9
Classifier: Programming Language :: Python :: 3.10
Classifier: Programming Language :: Python :: 3.11
Classifier: Programming Language :: Python :: 3.12
Classifier: Operating System :: OS Independent
Requires-Python: >=3.7
License-File: LICENSE
Requires-Dist: gradus>=1.0.1
Requires-Dist: resono>=1.0.1
Requires-Dist: shadowbits>=1.0.1
Dynamic: license-file
